README.txt
buildout.cfg
setup.py
collective/__init__.py
collective.subscribemember.egg-info/PKG-INFO
collective.subscribemember.egg-info/SOURCES.txt
collective.subscribemember.egg-info/dependency_links.txt
collective.subscribemember.egg-info/entry_points.txt
collective.subscribemember.egg-info/namespace_packages.txt
collective.subscribemember.egg-info/not-zip-safe
collective.subscribemember.egg-info/requires.txt
collective.subscribemember.egg-info/top_level.txt
collective/subscribemember/README.txt
collective/subscribemember/__init__.py
collective/subscribemember/adapters.py
collective/subscribemember/config.py
collective/subscribemember/configure.zcml
collective/subscribemember/events.py
collective/subscribemember/exporter.py
collective/subscribemember/interfaces.py
collective/subscribemember/memberexpiry.txt
collective/subscribemember/memberexport.txt
collective/subscribemember/memberimport.txt
collective/subscribemember/profiles.zcml
collective/subscribemember/setuphandlers.py
collective/subscribemember/subscribemember.txt
collective/subscribemember/subscribers.py
collective/subscribemember/utils.py
collective/subscribemember/vocabulary.py
collective/subscribemember/browser/__init__.py
collective/subscribemember/browser/configure.zcml
collective/subscribemember/browser/memberexpiry.py
collective/subscribemember/browser/memberexport.py
collective/subscribemember/browser/memberimport.py
collective/subscribemember/browser/renew.py
collective/subscribemember/browser/templates/renew_expired_view.pt
collective/subscribemember/browser/templates/subscribemembercheckout.pt
collective/subscribemember/content/__init__.py
collective/subscribemember/content/configure.zcml
collective/subscribemember/content/subscribemember.py
collective/subscribemember/profiles/default/browserlayer.xml
collective/subscribemember/profiles/default/catalog.xml
collective/subscribemember/profiles/default/metadata.xml
collective/subscribemember/profiles/default/propertiestool.xml
collective/subscribemember/profiles/default/rolemap.xml
collective/subscribemember/profiles/default/skins.xml
collective/subscribemember/profiles/default/subscribemember-setup-plugins.txt
collective/subscribemember/profiles/testing/browserlayer.xml
collective/subscribemember/profiles/testing/catalog.xml
collective/subscribemember/profiles/testing/metadata.xml
collective/subscribemember/profiles/testing/propertiestool.xml
