Metadata-Version: 1.0
Name: collective.subscribemember
Version: 1.0
Summary: A tool to allow users to subscribe to a Plone site and pay their membership fees.
Home-page: http://www.emergetec.com
Author: Tim Knapp
Author-email: tim@emergetec.com
License: GPL
Keywords: plone remember membrane plonegetpaid subscription membership
Platform: UNKNOWN
Classifier: Framework :: Plone
Classifier: Intended Audience :: Developers
Classifier: Topic :: Software Development :: Libraries :: Python Modules
Classifier: License :: OSI Approved :: GNU General Public License (GPL)
